{
  "$id": "http://example.com/example.json",
  "type": "object",
  "definitions": {},
  "$schema": "http://json-schema.org/draft-07/schema#",
  "properties": {
    "records": {
      "$id": "/properties/records",
      "type": "array",
      "items": {
        "$id": "/properties/records/items",
        "type": "object",
        "properties": {
          "record": {
            "$id": "/properties/records/items/properties/record",
            "type": "object",
            "properties": {
              "$attributes": {
                "$id": "/properties/records/items/properties/record/properties/$attributes",
                "type": "object",
                "properties": {
                  "$xsiType": {
                    "$id": "/properties/records/items/properties/record/properties/$attributes/properties/$xsiType",
                    "type": "object",
                    "properties": {
                      "tranSales": {
                        "$id": "/properties/records/items/properties/record/properties/$attributes/properties/$xsiType/properties/tranSales",
                        "type": "string",
                        "examples": [
                          "urn:sales_2017_1.transactions.webservices.netsuite.com"
                        ]
                      },
                      "type": {
                        "$id": "/properties/records/items/properties/record/properties/$attributes/properties/$xsiType/properties/type",
                        "type": "string",
                        "examples": [
                          "SalesOrder"
                        ]
                      }
                    }
                  },
                  "internalId": {
                    "$id": "/properties/records/items/properties/record/properties/$attributes/properties/internalId",
                    "type": "string",
                    "examples": [
                      "5731"
                    ]
                  }
                }
              },
              "createdDate": {
                "$id": "/properties/records/items/properties/record/properties/createdDate",
                "type": "string",
                "examples": [
                  "2018-04-01T15:33:46.000-07:00"
                ]
              },
              "customForm": {
                "$id": "/properties/records/items/properties/record/properties/customForm",
                "type": "object",
                "properties": {
                  "$attributes": {
                    "$id": "/properties/records/items/properties/record/properties/customForm/properties/$attributes",
                    "type": "object",
                    "properties": {
                      "$xsiType": {
                        "$id": "/properties/records/items/properties/record/properties/customForm/properties/$attributes/properties/$xsiType",
                        "type": "object",
                        "properties": {
                          "platformCore": {
                            "$id": "/properties/records/items/properties/record/properties/customForm/properties/$attributes/properties/$xsiType/properties/platformCore",
                            "type": "string",
                            "examples": [
                              "urn:core_2017_1.platform.webservices.netsuite.com"
                            ]
                          }
                        }
                      },
                      "internalId": {
                        "$id": "/properties/records/items/properties/record/properties/customForm/properties/$attributes/properties/internalId",
                        "type": "string",
                        "examples": [
                          "174"
                        ]
                      }
                    }
                  },
                  "name": {
                    "$id": "/properties/records/items/properties/record/properties/customForm/properties/name",
                    "type": "string",
                    "examples": [
                      "Z - HM Sales Order Form"
                    ]
                  }
                }
              },
              "entity": {
                "$id": "/properties/records/items/properties/record/properties/entity",
                "type": "object",
                "properties": {
                  "$attributes": {
                    "$id": "/properties/records/items/properties/record/properties/entity/properties/$attributes",
                    "type": "object",
                    "properties": {
                      "$xsiType": {
                        "$id": "/properties/records/items/properties/record/properties/entity/properties/$attributes/properties/$xsiType",
                        "type": "object",
                        "properties": {
                          "platformCore": {
                            "$id": "/properties/records/items/properties/record/properties/entity/properties/$attributes/properties/$xsiType/properties/platformCore",
                            "type": "string",
                            "examples": [
                              "urn:core_2017_1.platform.webservices.netsuite.com"
                            ]
                          }
                        }
                      },
                      "internalId": {
                        "$id": "/properties/records/items/properties/record/properties/entity/properties/$attributes/properties/internalId",
                        "type": "string",
                        "examples": [
                          "605"
                        ]
                      }
                    }
                  },
                  "name": {
                    "$id": "/properties/records/items/properties/record/properties/entity/properties/name",
                    "type": "string",
                    "examples": [
                      "Stower Electric Company"
                    ]
                  }
                }
              },
              "currency": {
                "$id": "/properties/records/items/properties/record/properties/currency",
                "type": "object",
                "properties": {
                  "$attributes": {
                    "$id": "/properties/records/items/properties/record/properties/currency/properties/$attributes",
                    "type": "object",
                    "properties": {
                      "$xsiType": {
                        "$id": "/properties/records/items/properties/record/properties/currency/properties/$attributes/properties/$xsiType",
                        "type": "object",
                        "properties": {
                          "platformCore": {
                            "$id": "/properties/records/items/properties/record/properties/currency/properties/$attributes/properties/$xsiType/properties/platformCore",
                            "type": "string",
                            "examples": [
                              "urn:core_2017_1.platform.webservices.netsuite.com"
                            ]
                          }
                        }
                      },
                      "internalId": {
                        "$id": "/properties/records/items/properties/record/properties/currency/properties/$attributes/properties/internalId",
                        "type": "string",
                        "examples": [
                          "1"
                        ]
                      }
                    }
                  },
                  "name": {
                    "$id": "/properties/records/items/properties/record/properties/currency/properties/name",
                    "type": "string",
                    "examples": [
                      "USA"
                    ]
                  }
                }
              },
              "tranDate": {
                "$id": "/properties/records/items/properties/record/properties/tranDate",
                "type": "string",
                "examples": [
                  "2018-04-02T00:00:00.000-07:00"
                ]
              },
              "tranId": {
                "$id": "/properties/records/items/properties/record/properties/tranId",
                "type": "string",
                "examples": [
                  "SLS00000549"
                ]
              },
              "nextBill": {
                "$id": "/properties/records/items/properties/record/properties/nextBill",
                "type": "string",
                "examples": [
                  "2018-04-02T00:00:00.000-07:00"
                ]
              },
              "totalCostEstimate": {
                "$id": "/properties/records/items/properties/record/properties/totalCostEstimate",
                "type": "string",
                "examples": [
                  "290.02"
                ]
              },
              "estGrossProfit": {
                "$id": "/properties/records/items/properties/record/properties/estGrossProfit",
                "type": "string",
                "examples": [
                  "440.93"
                ]
              },
              "estGrossProfitPercent": {
                "$id": "/properties/records/items/properties/record/properties/estGrossProfitPercent",
                "type": "string",
                "examples": [
                  "60.3229"
                ]
              },
              "exchangeRate": {
                "$id": "/properties/records/items/properties/record/properties/exchangeRate",
                "type": "string",
                "examples": [
                  "1.0"
                ]
              },
              "currencyName": {
                "$id": "/properties/records/items/properties/record/properties/currencyName",
                "type": "string",
                "examples": [
                  "USA"
                ]
              },
              "toBePrinted": {
                "$id": "/properties/records/items/properties/record/properties/toBePrinted",
                "type": "string",
                "examples": [
                  "false"
                ]
              },
              "toBeEmailed": {
                "$id": "/properties/records/items/properties/record/properties/toBeEmailed",
                "type": "string",
                "examples": [
                  "false"
                ]
              },
              "email": {
                "$id": "/properties/records/items/properties/record/properties/email",
                "type": "string",
                "examples": [
                  "DKuhnemund@laughers.net"
                ]
              },
              "toBeFaxed": {
                "$id": "/properties/records/items/properties/record/properties/toBeFaxed",
                "type": "string",
                "examples": [
                  "false"
                ]
              },
              "billingAddress": {
                "$id": "/properties/records/items/properties/record/properties/billingAddress",
                "type": "object",
                "properties": {
                  "$attributes": {
                    "$id": "/properties/records/items/properties/record/properties/billingAddress/properties/$attributes",
                    "type": "object",
                    "properties": {
                      "$xsiType": {
                        "$id": "/properties/records/items/properties/record/properties/billingAddress/properties/$attributes/properties/$xsiType",
                        "type": "object",
                        "properties": {
                          "platformCommon": {
                            "$id": "/properties/records/items/properties/record/properties/billingAddress/properties/$attributes/properties/$xsiType/properties/platformCommon",
                            "type": "string",
                            "examples": [
                              "urn:common_2017_1.platform.webservices.netsuite.com"
                            ]
                          }
                        }
                      }
                    }
                  },
                  "country": {
                    "$id": "/properties/records/items/properties/record/properties/billingAddress/properties/country",
                    "type": "string",
                    "examples": [
                      "_unitedStates"
                    ]
                  },
                  "addressee": {
                    "$id": "/properties/records/items/properties/record/properties/billingAddress/properties/addressee",
                    "type": "string",
                    "examples": [
                      "Stower Electric Company"
                    ]
                  },
                  "addr1": {
                    "$id": "/properties/records/items/properties/record/properties/billingAddress/properties/addr1",
                    "type": "string",
                    "examples": [
                      "8194 Bloomington  Road"
                    ]
                  },
                  "city": {
                    "$id": "/properties/records/items/properties/record/properties/billingAddress/properties/city",
                    "type": "string",
                    "examples": [
                      "La Habra"
                    ]
                  },
                  "state": {
                    "$id": "/properties/records/items/properties/record/properties/billingAddress/properties/state",
                    "type": "string",
                    "examples": [
                      "CA"
                    ]
                  },
                  "zip": {
                    "$id": "/properties/records/items/properties/record/properties/billingAddress/properties/zip",
                    "type": "string",
                    "examples": [
                      "90631"
                    ]
                  },
                  "addrText": {
                    "$id": "/properties/records/items/properties/record/properties/billingAddress/properties/addrText",
                    "type": "string",
                    "examples": [
                      "Stower Electric Company 8194 Bloomington Road La Habra, CA 90631"
                    ]
                  },
                  "override": {
                    "$id": "/properties/records/items/properties/record/properties/billingAddress/properties/override",
                    "type": "string",
                    "examples": [
                      "false"
                    ]
                  }
                }
              },
              "billAddressList": {
                "$id": "/properties/records/items/properties/record/properties/billAddressList",
                "type": "object",
                "properties": {
                  "$attributes": {
                    "$id": "/properties/records/items/properties/record/properties/billAddressList/properties/$attributes",
                    "type": "object",
                    "properties": {
                      "$xsiType": {
                        "$id": "/properties/records/items/properties/record/properties/billAddressList/properties/$attributes/properties/$xsiType",
                        "type": "object",
                        "properties": {
                          "platformCore": {
                            "$id": "/properties/records/items/properties/record/properties/billAddressList/properties/$attributes/properties/$xsiType/properties/platformCore",
                            "type": "string",
                            "examples": [
                              "urn:core_2017_1.platform.webservices.netsuite.com"
                            ]
                          }
                        }
                      },
                      "internalId": {
                        "$id": "/properties/records/items/properties/record/properties/billAddressList/properties/$attributes/properties/internalId",
                        "type": "string",
                        "examples": [
                          "244385"
                        ]
                      }
                    }
                  },
                  "name": {
                    "$id": "/properties/records/items/properties/record/properties/billAddressList/properties/name",
                    "type": "string",
                    "examples": [
                      "default bill address"
                    ]
                  }
                }
              },
              "shippingAddress": {
                "$id": "/properties/records/items/properties/record/properties/shippingAddress",
                "type": "object",
                "properties": {
                  "$attributes": {
                    "$id": "/properties/records/items/properties/record/properties/shippingAddress/properties/$attributes",
                    "type": "object",
                    "properties": {
                      "$xsiType": {
                        "$id": "/properties/records/items/properties/record/properties/shippingAddress/properties/$attributes/properties/$xsiType",
                        "type": "object",
                        "properties": {
                          "platformCommon": {
                            "$id": "/properties/records/items/properties/record/properties/shippingAddress/properties/$attributes/properties/$xsiType/properties/platformCommon",
                            "type": "string",
                            "examples": [
                              "urn:common_2017_1.platform.webservices.netsuite.com"
                            ]
                          }
                        }
                      }
                    }
                  },
                  "country": {
                    "$id": "/properties/records/items/properties/record/properties/shippingAddress/properties/country",
                    "type": "string",
                    "examples": [
                      "_unitedStates"
                    ]
                  },
                  "addressee": {
                    "$id": "/properties/records/items/properties/record/properties/shippingAddress/properties/addressee",
                    "type": "string",
                    "examples": [
                      "Stower Electric Company"
                    ]
                  },
                  "addr1": {
                    "$id": "/properties/records/items/properties/record/properties/shippingAddress/properties/addr1",
                    "type": "string",
                    "examples": [
                      "8194 Bloomington  Road"
                    ]
                  },
                  "city": {
                    "$id": "/properties/records/items/properties/record/properties/shippingAddress/properties/city",
                    "type": "string",
                    "examples": [
                      "La Habra"
                    ]
                  },
                  "state": {
                    "$id": "/properties/records/items/properties/record/properties/shippingAddress/properties/state",
                    "type": "string",
                    "examples": [
                      "CA"
                    ]
                  },
                  "zip": {
                    "$id": "/properties/records/items/properties/record/properties/shippingAddress/properties/zip",
                    "type": "string",
                    "examples": [
                      "90631"
                    ]
                  },
                  "addrText": {
                    "$id": "/properties/records/items/properties/record/properties/shippingAddress/properties/addrText",
                    "type": "string",
                    "examples": [
                      "Stower Electric Company 8194 Bloomington Road La Habra, CA 90631"
                    ]
                  },
                  "override": {
                    "$id": "/properties/records/items/properties/record/properties/shippingAddress/properties/override",
                    "type": "string",
                    "examples": [
                      "false"
                    ]
                  }
                }
              },
              "shipIsResidential": {
                "$id": "/properties/records/items/properties/record/properties/shipIsResidential",
                "type": "string",
                "examples": [
                  "false"
                ]
              },
              "shipAddressList": {
                "$id": "/properties/records/items/properties/record/properties/shipAddressList",
                "type": "object",
                "properties": {
                  "$attributes": {
                    "$id": "/properties/records/items/properties/record/properties/shipAddressList/properties/$attributes",
                    "type": "object",
                    "properties": {
                      "$xsiType": {
                        "$id": "/properties/records/items/properties/record/properties/shipAddressList/properties/$attributes/properties/$xsiType",
                        "type": "object",
                        "properties": {
                          "platformCore": {
                            "$id": "/properties/records/items/properties/record/properties/shipAddressList/properties/$attributes/properties/$xsiType/properties/platformCore",
                            "type": "string",
                            "examples": [
                              "urn:core_2017_1.platform.webservices.netsuite.com"
                            ]
                          }
                        }
                      },
                      "internalId": {
                        "$id": "/properties/records/items/properties/record/properties/shipAddressList/properties/$attributes/properties/internalId",
                        "type": "string",
                        "examples": [
                          "244385"
                        ]
                      }
                    }
                  },
                  "name": {
                    "$id": "/properties/records/items/properties/record/properties/shipAddressList/properties/name",
                    "type": "string",
                    "examples": [
                      "default bill address"
                    ]
                  }
                }
              },
              "shipDate": {
                "$id": "/properties/records/items/properties/record/properties/shipDate",
                "type": "string",
                "examples": [
                  "2018-04-04T00:00:00.000-07:00"
                ]
              },
              "shipMethod": {
                "$id": "/properties/records/items/properties/record/properties/shipMethod",
                "type": "object",
                "properties": {
                  "$attributes": {
                    "$id": "/properties/records/items/properties/record/properties/shipMethod/properties/$attributes",
                    "type": "object",
                    "properties": {
                      "$xsiType": {
                        "$id": "/properties/records/items/properties/record/properties/shipMethod/properties/$attributes/properties/$xsiType",
                        "type": "object",
                        "properties": {
                          "platformCore": {
                            "$id": "/properties/records/items/properties/record/properties/shipMethod/properties/$attributes/properties/$xsiType/properties/platformCore",
                            "type": "string",
                            "examples": [
                              "urn:core_2017_1.platform.webservices.netsuite.com"
                            ]
                          }
                        }
                      },
                      "internalId": {
                        "$id": "/properties/records/items/properties/record/properties/shipMethod/properties/$attributes/properties/internalId",
                        "type": "string",
                        "examples": [
                          "2"
                        ]
                      }
                    }
                  },
                  "name": {
                    "$id": "/properties/records/items/properties/record/properties/shipMethod/properties/name",
                    "type": "string",
                    "examples": [
                      "Pick-up at store"
                    ]
                  }
                }
              },
              "shippingCost": {
                "$id": "/properties/records/items/properties/record/properties/shippingCost",
                "type": "string",
                "examples": [
                  "0.0"
                ]
              },
              "isMultiShipTo": {
                "$id": "/properties/records/items/properties/record/properties/isMultiShipTo",
                "type": "string",
                "examples": [
                  "false"
                ]
              },
              "shippingTaxCode": {
                "$id": "/properties/records/items/properties/record/properties/shippingTaxCode",
                "type": "object",
                "properties": {
                  "$attributes": {
                    "$id": "/properties/records/items/properties/record/properties/shippingTaxCode/properties/$attributes",
                    "type": "object",
                    "properties": {
                      "$xsiType": {
                        "$id": "/properties/records/items/properties/record/properties/shippingTaxCode/properties/$attributes/properties/$xsiType",
                        "type": "object",
                        "properties": {
                          "platformCore": {
                            "$id": "/properties/records/items/properties/record/properties/shippingTaxCode/properties/$attributes/properties/$xsiType/properties/platformCore",
                            "type": "string",
                            "examples": [
                              "urn:core_2017_1.platform.webservices.netsuite.com"
                            ]
                          }
                        }
                      },
                      "internalId": {
                        "$id": "/properties/records/items/properties/record/properties/shippingTaxCode/properties/$attributes/properties/internalId",
                        "type": "string",
                        "examples": [
                          "-7"
                        ]
                      }
                    }
                  },
                  "name": {
                    "$id": "/properties/records/items/properties/record/properties/shippingTaxCode/properties/name",
                    "type": "string",
                    "examples": [
                      "-Not Taxable-"
                    ]
                  }
                }
              },
              "handlingCost": {
                "$id": "/properties/records/items/properties/record/properties/handlingCost",
                "type": "string",
                "examples": [
                  "0.0"
                ]
              },
              "shipComplete": {
                "$id": "/properties/records/items/properties/record/properties/shipComplete",
                "type": "string",
                "examples": [
                  "false"
                ]
              },
              "saveOnAuthDecline": {
                "$id": "/properties/records/items/properties/record/properties/saveOnAuthDecline",
                "type": "string",
                "examples": [
                  "true"
                ]
              },
              "canHaveStackable": {
                "$id": "/properties/records/items/properties/record/properties/canHaveStackable",
                "type": "string",
                "examples": [
                  "false"
                ]
              },
              "ccApproved": {
                "$id": "/properties/records/items/properties/record/properties/ccApproved",
                "type": "string",
                "examples": [
                  "false"
                ]
              },
              "getAuth": {
                "$id": "/properties/records/items/properties/record/properties/getAuth",
                "type": "string",
                "examples": [
                  "false"
                ]
              },
              "isRecurringPayment": {
                "$id": "/properties/records/items/properties/record/properties/isRecurringPayment",
                "type": "string",
                "examples": [
                  "false"
                ]
              },
              "subTotal": {
                "$id": "/properties/records/items/properties/record/properties/subTotal",
                "type": "string",
                "examples": [
                  "730.95"
                ]
              },
              "discountTotal": {
                "$id": "/properties/records/items/properties/record/properties/discountTotal",
                "type": "string",
                "examples": [
                  "0.0"
                ]
              },
              "taxTotal": {
                "$id": "/properties/records/items/properties/record/properties/taxTotal",
                "type": "string",
                "examples": [
                  "0.0"
                ]
              },
              "altShippingCost": {
                "$id": "/properties/records/items/properties/record/properties/altShippingCost",
                "type": "string",
                "examples": [
                  "0.0"
                ]
              },
              "total": {
                "$id": "/properties/records/items/properties/record/properties/total",
                "type": "string",
                "examples": [
                  "730.95"
                ]
              },
              "balance": {
                "$id": "/properties/records/items/properties/record/properties/balance",
                "type": "string",
                "examples": [
                  "31.95"
                ]
              },
              "paypalProcess": {
                "$id": "/properties/records/items/properties/record/properties/paypalProcess",
                "type": "string",
                "examples": [
                  "false"
                ]
              },
              "subsidiary": {
                "$id": "/properties/records/items/properties/record/properties/subsidiary",
                "type": "object",
                "properties": {
                  "$attributes": {
                    "$id": "/properties/records/items/properties/record/properties/subsidiary/properties/$attributes",
                    "type": "object",
                    "properties": {
                      "$xsiType": {
                        "$id": "/properties/records/items/properties/record/properties/subsidiary/properties/$attributes/properties/$xsiType",
                        "type": "object",
                        "properties": {
                          "platformCore": {
                            "$id": "/properties/records/items/properties/record/properties/subsidiary/properties/$attributes/properties/$xsiType/properties/platformCore",
                            "type": "string",
                            "examples": [
                              "urn:core_2017_1.platform.webservices.netsuite.com"
                            ]
                          }
                        }
                      },
                      "internalId": {
                        "$id": "/properties/records/items/properties/record/properties/subsidiary/properties/$attributes/properties/internalId",
                        "type": "string",
                        "examples": [
                          "1"
                        ]
                      }
                    }
                  },
                  "name": {
                    "$id": "/properties/records/items/properties/record/properties/subsidiary/properties/name",
                    "type": "string",
                    "examples": [
                      "Honeycomb Mfg."
                    ]
                  }
                }
              },
              "lastModifiedDate": {
                "$id": "/properties/records/items/properties/record/properties/lastModifiedDate",
                "type": "string",
                "examples": [
                  "2018-04-05T06:42:10.000-07:00"
                ]
              },
              "location": {
                "$id": "/properties/records/items/properties/record/properties/location",
                "type": "object",
                "properties": {
                  "$attributes": {
                    "$id": "/properties/records/items/properties/record/properties/location/properties/$attributes",
                    "type": "object",
                    "properties": {
                      "$xsiType": {
                        "$id": "/properties/records/items/properties/record/properties/location/properties/$attributes/properties/$xsiType",
                        "type": "object",
                        "properties": {
                          "platformCore": {
                            "$id": "/properties/records/items/properties/record/properties/location/properties/$attributes/properties/$xsiType/properties/platformCore",
                            "type": "string",
                            "examples": [
                              "urn:core_2017_1.platform.webservices.netsuite.com"
                            ]
                          }
                        }
                      },
                      "internalId": {
                        "$id": "/properties/records/items/properties/record/properties/location/properties/$attributes/properties/internalId",
                        "type": "string",
                        "examples": [
                          "2"
                        ]
                      }
                    }
                  },
                  "name": {
                    "$id": "/properties/records/items/properties/record/properties/location/properties/name",
                    "type": "string",
                    "examples": [
                      "01: San Francisco"
                    ]
                  }
                }
              },
              "status": {
                "$id": "/properties/records/items/properties/record/properties/status",
                "type": "string",
                "examples": [
                  "Partially Fulfilled"
                ]
              },
              "terms": {
                "$id": "/properties/records/items/properties/record/properties/terms",
                "type": "object",
                "properties": {
                  "$attributes": {
                    "$id": "/properties/records/items/properties/record/properties/terms/properties/$attributes",
                    "type": "object",
                    "properties": {
                      "$xsiType": {
                        "$id": "/properties/records/items/properties/record/properties/terms/properties/$attributes/properties/$xsiType",
                        "type": "object",
                        "properties": {
                          "platformCore": {
                            "$id": "/properties/records/items/properties/record/properties/terms/properties/$attributes/properties/$xsiType/properties/platformCore",
                            "type": "string",
                            "examples": [
                              "urn:core_2017_1.platform.webservices.netsuite.com"
                            ]
                          }
                        }
                      },
                      "internalId": {
                        "$id": "/properties/records/items/properties/record/properties/terms/properties/$attributes/properties/internalId",
                        "type": "string",
                        "examples": [
                          "2"
                        ]
                      }
                    }
                  },
                  "name": {
                    "$id": "/properties/records/items/properties/record/properties/terms/properties/name",
                    "type": "string",
                    "examples": [
                      "Net 30"
                    ]
                  }
                }
              },
              "itemList": {
                "$id": "/properties/records/items/properties/record/properties/itemList",
                "type": "object",
                "properties": {
                  "item": {
                    "$id": "/properties/records/items/properties/record/properties/itemList/properties/item",
                    "type": "array",
                    "items": {
                      "$id": "/properties/records/items/properties/record/properties/itemList/properties/item/items",
                      "type": "object",
                      "properties": {
                        "item": {
                          "$id": "/properties/records/items/properties/record/properties/itemList/properties/item/items/properties/item",
                          "type": "object",
                          "properties": {
                            "$attributes": {
                              "$id": "/properties/records/items/properties/record/properties/itemList/properties/item/items/properties/item/properties/$attributes",
                              "type": "object",
                              "properties": {
                                "$xsiType": {
                                  "$id": "/properties/records/items/properties/record/properties/itemList/properties/item/items/properties/item/properties/$attributes/properties/$xsiType",
                                  "type": "object",
                                  "properties": {
                                    "platformCore": {
                                      "$id": "/properties/records/items/properties/record/properties/itemList/properties/item/items/properties/item/properties/$attributes/properties/$xsiType/properties/platformCore",
                                      "type": "string",
                                      "examples": [
                                        "urn:core_2017_1.platform.webservices.netsuite.com"
                                      ]
                                    }
                                  }
                                },
                                "internalId": {
                                  "$id": "/properties/records/items/properties/record/properties/itemList/properties/item/items/properties/item/properties/$attributes/properties/internalId",
                                  "type": "string",
                                  "examples": [
                                    "38"
                                  ]
                                }
                              }
                            },
                            "name": {
                              "$id": "/properties/records/items/properties/record/properties/itemList/properties/item/items/properties/item/properties/name",
                              "type": "string",
                              "examples": [
                                "PRI00002"
                              ]
                            }
                          }
                        },
                        "quantityAvailable": {
                          "$id": "/properties/records/items/properties/record/properties/itemList/properties/item/items/properties/quantityAvailable",
                          "type": "string",
                          "examples": [
                            "0.0"
                          ]
                        },
                        "expandItemGroup": {
                          "$id": "/properties/records/items/properties/record/properties/itemList/properties/item/items/properties/expandItemGroup",
                          "type": "string",
                          "examples": [
                            "false"
                          ]
                        },
                        "lineUniqueKey": {
                          "$id": "/properties/records/items/properties/record/properties/itemList/properties/item/items/properties/lineUniqueKey",
                          "type": "string",
                          "examples": [
                            "25304"
                          ]
                        },
                        "quantityOnHand": {
                          "$id": "/properties/records/items/properties/record/properties/itemList/properties/item/items/properties/quantityOnHand",
                          "type": "string",
                          "examples": [
                            "-3.0"
                          ]
                        },
                        "quantity": {
                          "$id": "/properties/records/items/properties/record/properties/itemList/properties/item/items/properties/quantity",
                          "type": "string",
                          "examples": [
                            "1.0"
                          ]
                        },
                        "units": {
                          "$id": "/properties/records/items/properties/record/properties/itemList/properties/item/items/properties/units",
                          "type": "object",
                          "properties": {
                            "$attributes": {
                              "$id": "/properties/records/items/properties/record/properties/itemList/properties/item/items/properties/units/properties/$attributes",
                              "type": "object",
                              "properties": {
                                "$xsiType": {
                                  "$id": "/properties/records/items/properties/record/properties/itemList/properties/item/items/properties/units/properties/$attributes/properties/$xsiType",
                                  "type": "object",
                                  "properties": {
                                    "platformCore": {
                                      "$id": "/properties/records/items/properties/record/properties/itemList/properties/item/items/properties/units/properties/$attributes/properties/$xsiType/properties/platformCore",
                                      "type": "string",
                                      "examples": [
                                        "urn:core_2017_1.platform.webservices.netsuite.com"
                                      ]
                                    }
                                  }
                                },
                                "internalId": {
                                  "$id": "/properties/records/items/properties/record/properties/itemList/properties/item/items/properties/units/properties/$attributes/properties/internalId",
                                  "type": "string",
                                  "examples": [
                                    "1"
                                  ]
                                }
                              }
                            },
                            "name": {
                              "$id": "/properties/records/items/properties/record/properties/itemList/properties/item/items/properties/units/properties/name",
                              "type": "string",
                              "examples": [
                                "Ea"
                              ]
                            }
                          }
                        },
                        "description": {
                          "$id": "/properties/records/items/properties/record/properties/itemList/properties/item/items/properties/description",
                          "type": "string",
                          "examples": [
                            "ManuScript 1000 Laser Printer - 1200 dpi b&w"
                          ]
                        },
                        "price": {
                          "$id": "/properties/records/items/properties/record/properties/itemList/properties/item/items/properties/price",
                          "type": "object",
                          "properties": {
                            "$attributes": {
                              "$id": "/properties/records/items/properties/record/properties/itemList/properties/item/items/properties/price/properties/$attributes",
                              "type": "object",
                              "properties": {
                                "$xsiType": {
                                  "$id": "/properties/records/items/properties/record/properties/itemList/properties/item/items/properties/price/properties/$attributes/properties/$xsiType",
                                  "type": "object",
                                  "properties": {
                                    "platformCore": {
                                      "$id": "/properties/records/items/properties/record/properties/itemList/properties/item/items/properties/price/properties/$attributes/properties/$xsiType/properties/platformCore",
                                      "type": "string",
                                      "examples": [
                                        "urn:core_2017_1.platform.webservices.netsuite.com"
                                      ]
                                    }
                                  }
                                },
                                "internalId": {
                                  "$id": "/properties/records/items/properties/record/properties/itemList/properties/item/items/properties/price/properties/$attributes/properties/internalId",
                                  "type": "string",
                                  "examples": [
                                    "1"
                                  ]
                                }
                              }
                            },
                            "name": {
                              "$id": "/properties/records/items/properties/record/properties/itemList/properties/item/items/properties/price/properties/name",
                              "type": "string",
                              "examples": [
                                "List Price"
                              ]
                            }
                          }
                        },
                        "rate": {
                          "$id": "/properties/records/items/properties/record/properties/itemList/properties/item/items/properties/rate",
                          "type": "string",
                          "examples": [
                            "699.00"
                          ]
                        },
                        "amount": {
                          "$id": "/properties/records/items/properties/record/properties/itemList/properties/item/items/properties/amount",
                          "type": "string",
                          "examples": [
                            "699.0"
                          ]
                        },
                        "commitInventory": {
                          "$id": "/properties/records/items/properties/record/properties/itemList/properties/item/items/properties/commitInventory",
                          "type": "string",
                          "examples": [
                            "_availableQty"
                          ]
                        },
                        "location": {
                          "$id": "/properties/records/items/properties/record/properties/itemList/properties/item/items/properties/location",
                          "type": "object",
                          "properties": {
                            "$attributes": {
                              "$id": "/properties/records/items/properties/record/properties/itemList/properties/item/items/properties/location/properties/$attributes",
                              "type": "object",
                              "properties": {
                                "$xsiType": {
                                  "$id": "/properties/records/items/properties/record/properties/itemList/properties/item/items/properties/location/properties/$attributes/properties/$xsiType",
                                  "type": "object",
                                  "properties": {
                                    "platformCore": {
                                      "$id": "/properties/records/items/properties/record/properties/itemList/properties/item/items/properties/location/properties/$attributes/properties/$xsiType/properties/platformCore",
                                      "type": "string",
                                      "examples": [
                                        "urn:core_2017_1.platform.webservices.netsuite.com"
                                      ]
                                    }
                                  }
                                },
                                "internalId": {
                                  "$id": "/properties/records/items/properties/record/properties/itemList/properties/item/items/properties/location/properties/$attributes/properties/internalId",
                                  "type": "string",
                                  "examples": [
                                    "2"
                                  ]
                                }
                              }
                            },
                            "name": {
                              "$id": "/properties/records/items/properties/record/properties/itemList/properties/item/items/properties/location/properties/name",
                              "type": "string",
                              "examples": [
                                "01: San Francisco"
                              ]
                            }
                          }
                        },
                        "createWo": {
                          "$id": "/properties/records/items/properties/record/properties/itemList/properties/item/items/properties/createWo",
                          "type": "string",
                          "examples": [
                            "false"
                          ]
                        },
                        "fromJob": {
                          "$id": "/properties/records/items/properties/record/properties/itemList/properties/item/items/properties/fromJob",
                          "type": "string",
                          "examples": [
                            "false"
                          ]
                        },
                        "isEstimate": {
                          "$id": "/properties/records/items/properties/record/properties/itemList/properties/item/items/properties/isEstimate",
                          "type": "string",
                          "examples": [
                            "false"
                          ]
                        },
                        "line": {
                          "$id": "/properties/records/items/properties/record/properties/itemList/properties/item/items/properties/line",
                          "type": "string",
                          "examples": [
                            "1"
                          ]
                        },
                        "taxCode": {
                          "$id": "/properties/records/items/properties/record/properties/itemList/properties/item/items/properties/taxCode",
                          "type": "object",
                          "properties": {
                            "$attributes": {
                              "$id": "/properties/records/items/properties/record/properties/itemList/properties/item/items/properties/taxCode/properties/$attributes",
                              "type": "object",
                              "properties": {
                                "$xsiType": {
                                  "$id": "/properties/records/items/properties/record/properties/itemList/properties/item/items/properties/taxCode/properties/$attributes/properties/$xsiType",
                                  "type": "object",
                                  "properties": {
                                    "platformCore": {
                                      "$id": "/properties/records/items/properties/record/properties/itemList/properties/item/items/properties/taxCode/properties/$attributes/properties/$xsiType/properties/platformCore",
                                      "type": "string",
                                      "examples": [
                                        "urn:core_2017_1.platform.webservices.netsuite.com"
                                      ]
                                    }
                                  }
                                },
                                "internalId": {
                                  "$id": "/properties/records/items/properties/record/properties/itemList/properties/item/items/properties/taxCode/properties/$attributes/properties/internalId",
                                  "type": "string",
                                  "examples": [
                                    "-7"
                                  ]
                                }
                              }
                            },
                            "name": {
                              "$id": "/properties/records/items/properties/record/properties/itemList/properties/item/items/properties/taxCode/properties/name",
                              "type": "string",
                              "examples": [
                                "-Not Taxable-"
                              ]
                            }
                          }
                        },
                        "shipGroup": {
                          "$id": "/properties/records/items/properties/record/properties/itemList/properties/item/items/properties/shipGroup",
                          "type": "string",
                          "examples": [
                            "1"
                          ]
                        },
                        "itemIsFulfilled": {
                          "$id": "/properties/records/items/properties/record/properties/itemList/properties/item/items/properties/itemIsFulfilled",
                          "type": "string",
                          "examples": [
                            "false"
                          ]
                        }
                      }
                    }
                  }
                }
              },
              "shipGroupList": {
                "$id": "/properties/records/items/properties/record/properties/shipGroupList",
                "type": "object",
                "properties": {
                  "shipGroup": {
                    "$id": "/properties/records/items/properties/record/properties/shipGroupList/properties/shipGroup",
                    "type": "object",
                    "properties": {
                      "id": {
                        "$id": "/properties/records/items/properties/record/properties/shipGroupList/properties/shipGroup/properties/id",
                        "type": "string",
                        "examples": [
                          "1"
                        ]
                      },
                      "isFulfilled": {
                        "$id": "/properties/records/items/properties/record/properties/shipGroupList/properties/shipGroup/properties/isFulfilled",
                        "type": "string",
                        "examples": [
                          "false"
                        ]
                      },
                      "weight": {
                        "$id": "/properties/records/items/properties/record/properties/shipGroupList/properties/shipGroup/properties/weight",
                        "type": "string",
                        "examples": [
                          "33.0"
                        ]
                      },
                      "sourceAddressRef": {
                        "$id": "/properties/records/items/properties/record/properties/shipGroupList/properties/shipGroup/properties/sourceAddressRef",
                        "type": "object",
                        "properties": {
                          "$attributes": {
                            "$id": "/properties/records/items/properties/record/properties/shipGroupList/properties/shipGroup/properties/sourceAddressRef/properties/$attributes",
                            "type": "object",
                            "properties": {
                              "$xsiType": {
                                "$id": "/properties/records/items/properties/record/properties/shipGroupList/properties/shipGroup/properties/sourceAddressRef/properties/$attributes/properties/$xsiType",
                                "type": "object",
                                "properties": {
                                  "platformCore": {
                                    "$id": "/properties/records/items/properties/record/properties/shipGroupList/properties/shipGroup/properties/sourceAddressRef/properties/$attributes/properties/$xsiType/properties/platformCore",
                                    "type": "string",
                                    "examples": [
                                      "urn:core_2017_1.platform.webservices.netsuite.com"
                                    ]
                                  }
                                }
                              },
                              "internalId": {
                                "$id": "/properties/records/items/properties/record/properties/shipGroupList/properties/shipGroup/properties/sourceAddressRef/properties/$attributes/properties/internalId",
                                "type": "string",
                                "examples": [
                                  "DEFAULT"
                                ]
                              }
                            }
                          }
                        }
                      },
                      "destinationAddressRef": {
                        "$id": "/properties/records/items/properties/record/properties/shipGroupList/properties/shipGroup/properties/destinationAddressRef",
                        "type": "object",
                        "properties": {
                          "$attributes": {
                            "$id": "/properties/records/items/properties/record/properties/shipGroupList/properties/shipGroup/properties/destinationAddressRef/properties/$attributes",
                            "type": "object",
                            "properties": {
                              "$xsiType": {
                                "$id": "/properties/records/items/properties/record/properties/shipGroupList/properties/shipGroup/properties/destinationAddressRef/properties/$attributes/properties/$xsiType",
                                "type": "object",
                                "properties": {
                                  "platformCore": {
                                    "$id": "/properties/records/items/properties/record/properties/shipGroupList/properties/shipGroup/properties/destinationAddressRef/properties/$attributes/properties/$xsiType/properties/platformCore",
                                    "type": "string",
                                    "examples": [
                                      "urn:core_2017_1.platform.webservices.netsuite.com"
                                    ]
                                  }
                                }
                              },
                              "internalId": {
                                "$id": "/properties/records/items/properties/record/properties/shipGroupList/properties/shipGroup/properties/destinationAddressRef/properties/$attributes/properties/internalId",
                                "type": "string",
                                "examples": [
                                  "244385"
                                ]
                              }
                            }
                          }
                        }
                      },
                      "destinationAddress": {
                        "$id": "/properties/records/items/properties/record/properties/shipGroupList/properties/shipGroup/properties/destinationAddress",
                        "type": "string",
                        "examples": [
                          "8194 Bloomington Road La Habra CA 90631 United States"
                        ]
                      },
                      "shippingMethodRef": {
                        "$id": "/properties/records/items/properties/record/properties/shipGroupList/properties/shipGroup/properties/shippingMethodRef",
                        "type": "object",
                        "properties": {
                          "$attributes": {
                            "$id": "/properties/records/items/properties/record/properties/shipGroupList/properties/shipGroup/properties/shippingMethodRef/properties/$attributes",
                            "type": "object",
                            "properties": {
                              "$xsiType": {
                                "$id": "/properties/records/items/properties/record/properties/shipGroupList/properties/shipGroup/properties/shippingMethodRef/properties/$attributes/properties/$xsiType",
                                "type": "object",
                                "properties": {
                                  "platformCore": {
                                    "$id": "/properties/records/items/properties/record/properties/shipGroupList/properties/shipGroup/properties/shippingMethodRef/properties/$attributes/properties/$xsiType/properties/platformCore",
                                    "type": "string",
                                    "examples": [
                                      "urn:core_2017_1.platform.webservices.netsuite.com"
                                    ]
                                  }
                                }
                              },
                              "internalId": {
                                "$id": "/properties/records/items/properties/record/properties/shipGroupList/properties/shipGroup/properties/shippingMethodRef/properties/$attributes/properties/internalId",
                                "type": "string",
                                "examples": [
                                  "2"
                                ]
                              }
                            }
                          }
                        }
                      },
                      "shippingMethod": {
                        "$id": "/properties/records/items/properties/record/properties/shipGroupList/properties/shipGroup/properties/shippingMethod",
                        "type": "string",
                        "examples": [
                          "Pick-up at store"
                        ]
                      },
                      "handlingTaxCode": {
                        "$id": "/properties/records/items/properties/record/properties/shipGroupList/properties/shipGroup/properties/handlingTaxCode",
                        "type": "object",
                        "properties": {
                          "$attributes": {
                            "$id": "/properties/records/items/properties/record/properties/shipGroupList/properties/shipGroup/properties/handlingTaxCode/properties/$attributes",
                            "type": "object",
                            "properties": {
                              "$xsiType": {
                                "$id": "/properties/records/items/properties/record/properties/shipGroupList/properties/shipGroup/properties/handlingTaxCode/properties/$attributes/properties/$xsiType",
                                "type": "object",
                                "properties": {
                                  "platformCore": {
                                    "$id": "/properties/records/items/properties/record/properties/shipGroupList/properties/shipGroup/properties/handlingTaxCode/properties/$attributes/properties/$xsiType/properties/platformCore",
                                    "type": "string",
                                    "examples": [
                                      "urn:core_2017_1.platform.webservices.netsuite.com"
                                    ]
                                  }
                                }
                              },
                              "internalId": {
                                "$id": "/properties/records/items/properties/record/properties/shipGroupList/properties/shipGroup/properties/handlingTaxCode/properties/$attributes/properties/internalId",
                                "type": "string",
                                "examples": [
                                  "-7"
                                ]
                              }
                            }
                          },
                          "name": {
                            "$id": "/properties/records/items/properties/record/properties/shipGroupList/properties/shipGroup/properties/handlingTaxCode/properties/name",
                            "type": "string",
                            "examples": [
                              "-Not Taxable-"
                            ]
                          }
                        }
                      },
                      "handlingRate": {
                        "$id": "/properties/records/items/properties/record/properties/shipGroupList/properties/shipGroup/properties/handlingRate",
                        "type": "string",
                        "examples": [
                          "0.0"
                        ]
                      },
                      "handlingTaxAmt": {
                        "$id": "/properties/records/items/properties/record/properties/shipGroupList/properties/shipGroup/properties/handlingTaxAmt",
                        "type": "string",
                        "examples": [
                          "0.0"
                        ]
                      },
                      "shippingTaxCode": {
                        "$id": "/properties/records/items/properties/record/properties/shipGroupList/properties/shipGroup/properties/shippingTaxCode",
                        "type": "object",
                        "properties": {
                          "$attributes": {
                            "$id": "/properties/records/items/properties/record/properties/shipGroupList/properties/shipGroup/properties/shippingTaxCode/properties/$attributes",
                            "type": "object",
                            "properties": {
                              "$xsiType": {
                                "$id": "/properties/records/items/properties/record/properties/shipGroupList/properties/shipGroup/properties/shippingTaxCode/properties/$attributes/properties/$xsiType",
                                "type": "object",
                                "properties": {
                                  "platformCore": {
                                    "$id": "/properties/records/items/properties/record/properties/shipGroupList/properties/shipGroup/properties/shippingTaxCode/properties/$attributes/properties/$xsiType/properties/platformCore",
                                    "type": "string",
                                    "examples": [
                                      "urn:core_2017_1.platform.webservices.netsuite.com"
                                    ]
                                  }
                                }
                              },
                              "internalId": {
                                "$id": "/properties/records/items/properties/record/properties/shipGroupList/properties/shipGroup/properties/shippingTaxCode/properties/$attributes/properties/internalId",
                                "type": "string",
                                "examples": [
                                  "-7"
                                ]
                              }
                            }
                          },
                          "name": {
                            "$id": "/properties/records/items/properties/record/properties/shipGroupList/properties/shipGroup/properties/shippingTaxCode/properties/name",
                            "type": "string",
                            "examples": [
                              "-Not Taxable-"
                            ]
                          }
                        }
                      },
                      "shippingRate": {
                        "$id": "/properties/records/items/properties/record/properties/shipGroupList/properties/shipGroup/properties/shippingRate",
                        "type": "string",
                        "examples": [
                          "0.0"
                        ]
                      },
                      "shippingTaxAmt": {
                        "$id": "/properties/records/items/properties/record/properties/shipGroupList/properties/shipGroup/properties/shippingTaxAmt",
                        "type": "string",
                        "examples": [
                          "0.0"
                        ]
                      }
                    }
                  }
                }
              },
              "customFieldList": {
                "$id": "/properties/records/items/properties/record/properties/customFieldList",
                "type": "object",
                "properties": {
                  "$attributes": {
                    "$id": "/properties/records/items/properties/record/properties/customFieldList/properties/$attributes",
                    "type": "object",
                    "properties": {
                      "$xsiType": {
                        "$id": "/properties/records/items/properties/record/properties/customFieldList/properties/$attributes/properties/$xsiType",
                        "type": "object",
                        "properties": {
                          "platformCore": {
                            "$id": "/properties/records/items/properties/record/properties/customFieldList/properties/$attributes/properties/$xsiType/properties/platformCore",
                            "type": "string",
                            "examples": [
                              "urn:core_2017_1.platform.webservices.netsuite.com"
                            ]
                          }
                        }
                      }
                    }
                  },
                  "customField": {
                    "$id": "/properties/records/items/properties/record/properties/customFieldList/properties/customField",
                    "type": "array",
                    "items": {
                      "$id": "/properties/records/items/properties/record/properties/customFieldList/properties/customField/items",
                      "type": "object",
                      "properties": {
                        "$attributes": {
                          "$id": "/properties/records/items/properties/record/properties/customFieldList/properties/customField/items/properties/$attributes",
                          "type": "object",
                          "properties": {
                            "$xsiType": {
                              "$id": "/properties/records/items/properties/record/properties/customFieldList/properties/customField/items/properties/$attributes/properties/$xsiType",
                              "type": "object",
                              "properties": {
                                "type": {
                                  "$id": "/properties/records/items/properties/record/properties/customFieldList/properties/customField/items/properties/$attributes/properties/$xsiType/properties/type",
                                  "type": "string",
                                  "examples": [
                                    "DateCustomFieldRef"
                                  ]
                                }
                              }
                            },
                            "internalId": {
                              "$id": "/properties/records/items/properties/record/properties/customFieldList/properties/customField/items/properties/$attributes/properties/internalId",
                              "type": "string",
                              "examples": [
                                "4"
                              ]
                            },
                            "scriptId": {
                              "$id": "/properties/records/items/properties/record/properties/customFieldList/properties/customField/items/properties/$attributes/properties/scriptId",
                              "type": "string",
                              "examples": [
                                "script_name"
                              ]
                            }
                          }
                        },
                        "value": {
                          "$id": "/properties/records/items/properties/record/properties/customFieldList/properties/customField/items/properties/value",
                          "type": "string",
                          "examples": [
                            "2018-04-05T00:00:00.000-07:00"
                          ]
                        }
                      }
                    }
                  }
                }
              }
            }
          }
        }
      }
    }
  }
}
